{"mean":{"confidence_interval":{"confidence_level":0.95,"lower_bound":7143.042634795301,"upper_bound":7278.872990267286},"point_estimate":7210.273751939876,"standard_error":34.59971945354976},"median":{"confidence_interval":{"confidence_level":0.95,"lower_bound":6930.001224489796,"upper_bound":7319.220068027211},"point_estimate":7134.64918487395,"standard_error":96.80605979848609},"median_abs_dev":{"confidence_interval":{"confidence_level":0.95,"lower_bound":114.41140789736278,"upper_bound":533.1923629261847},"point_estimate":393.3943395099721,"standard_error":110.10076868535576},"slope":{"confidence_interval":{"confidence_level":0.95,"lower_bound":7118.919509001637,"upper_bound":7279.781902622245},"point_estimate":7197.648777660495,"standard_error":41.1231897577548},"std_dev":{"confidence_interval":{"confidence_level":0.95,"lower_bound":307.67083995355534,"upper_bound":380.38604405528486},"point_estimate":346.35518110702833,"standard_error":18.539423766033337}}