{"mean":{"confidence_interval":{"confidence_level":0.95,"lower_bound":2960782.12367647,"upper_bound":2974360.363794119},"point_estimate":2967585.140588236,"standard_error":3473.2224986295705},"median":{"confidence_interval":{"confidence_level":0.95,"lower_bound":2961187.529411765,"upper_bound":2976606.882352941},"point_estimate":2967368.676470588,"standard_error":4171.200611829503},"median_abs_dev":{"confidence_interval":{"confidence_level":0.95,"lower_bound":29112.420294915908,"upper_bound":44689.138888962334},"point_estimate":37404.81997710792,"standard_error":4090.7302550209592},"slope":null,"std_dev":{"confidence_interval":{"confidence_level":0.95,"lower_bound":30317.52211496526,"upper_bound":39157.48240156601},"point_estimate":34986.09261080589,"standard_error":2254.1345745068134}}